odoo/addons/web_decimal_numpad_dot/README.rst
odoo/addons/web_decimal_numpad_dot/__init__.py
odoo/addons/web_decimal_numpad_dot/__manifest__.py
odoo/addons/web_decimal_numpad_dot/i18n/ca.po
odoo/addons/web_decimal_numpad_dot/i18n/es.po
odoo/addons/web_decimal_numpad_dot/i18n/es_ES.po
odoo/addons/web_decimal_numpad_dot/i18n/pt_BR.po
odoo/addons/web_decimal_numpad_dot/i18n/web_decimal_numpad_dot.pot
odoo/addons/web_decimal_numpad_dot/i18n/zh_CN.po
odoo/addons/web_decimal_numpad_dot/readme/CONTRIBUTORS.rst
odoo/addons/web_decimal_numpad_dot/readme/DESCRIPTION.rst
odoo/addons/web_decimal_numpad_dot/readme/USAGE.rst
odoo/addons/web_decimal_numpad_dot/static/description/icon.png
odoo/addons/web_decimal_numpad_dot/static/description/index.html
odoo/addons/web_decimal_numpad_dot/static/src/js/numpad_dot.js
odoo/addons/web_decimal_numpad_dot/views/web_decimal_numpad_dot.xml
odoo12_addon_web_decimal_numpad_dot-12.0.1.0.0.99.dev13.dist-info/METADATA
odoo12_addon_web_decimal_numpad_dot-12.0.1.0.0.99.dev13.dist-info/WHEEL
odoo12_addon_web_decimal_numpad_dot-12.0.1.0.0.99.dev13.dist-info/top_level.txt
odoo12_addon_web_decimal_numpad_dot-12.0.1.0.0.99.dev13.dist-info/RECORD
